ASIC/rtl/multispike_mod.sv
`timescale 1ns / 1ps

module multispike_mod #(
    parameter WIDTH = 1,
    parameter LENGTH = 4,
    parameter MAX_SPIKES = 16
)(
    input  logic clk,
    input  logic rst,
    input  logic clk_en,
    input  logic sample_pulse,
    input  logic [WIDTH-1:0][LENGTH-1:0] data_in,
    input  logic [15:0] divider,
    output logic [WIDTH-1:0] spikeP,
    output logic [WIDTH-1:0] spikeN
);

    assign spikeN = '0;

    localparam SPIKE_BITS = $clog2(MAX_SPIKES + 1);

    logic [WIDTH-1:0][SPIKE_BITS-1:0] num_spikes;
    logic [WIDTH-1:0][SPIKE_BITS-1:0] spike_count;
    logic [WIDTH-1:0][15:0] spike_interval;
    logic [WIDTH-1:0][15:0] interval_counter;
    logic [WIDTH-1:0][SPIKE_BITS-1:0] temp_spikes;

    always_ff @(posedge clk) begin
        if (rst) begin
            for (int i = 0; i < WIDTH; i++) begin
                num_spikes[i]       <= '0;
                spike_count[i]      <= '0;
                spike_interval[i]   <= '1;
                interval_counter[i] <= '0;
                spikeP[i]           <= 1'b0;
                temp_spikes[i]      <= '0;
            end
        end else if (clk_en) begin
            for (int i = 0; i < WIDTH; i++) begin
                if (sample_pulse) begin
                    temp_spikes[i] <= (data_in[i] * MAX_SPIKES) >> LENGTH;
                    num_spikes[i]  <= (data_in[i] * MAX_SPIKES) >> LENGTH;

                    if (((data_in[i] * MAX_SPIKES) >> LENGTH) == 0) begin
                        spike_interval[i] <= '1;
                    end else begin
                        spike_interval[i] <= (divider << 1) / ((data_in[i] * MAX_SPIKES) >> LENGTH);
                    end

                    spike_count[i]      <= '0;
                    interval_counter[i] <= '0;
                    spikeP[i]           <= 1'b0;
                end else begin
                    interval_counter[i] <= interval_counter[i] + 1'b1;

                    if (
                        spike_count[i] < num_spikes[i] &&
                        interval_counter[i] >= spike_interval[i]
                    ) begin
                        spikeP[i]           <= 1'b1;
                        spike_count[i]      <= spike_count[i] + 1'b1;
                        interval_counter[i] <= '0;
                    end else begin
                        spikeP[i] <= 1'b0;
                    end
                end
            end
        end else begin
            spikeP <= '0;
        end
    end

endmodule

ASIC/rtl/delta_mod.sv
module delta_mod #(
    parameter int WIDTH = 1,
    parameter int LENGTH = 4,
    parameter int JUMP = 5
)(
    input  logic clk,
    input  logic rst,
    input  logic clk_en,
    input  logic sample_pulse,
    input  logic [WIDTH*LENGTH-1:0] data_in,
    input  logic [15:0] divider,
    output logic [WIDTH-1:0] spikeP,
    output logic [WIDTH-1:0] spikeN
);

    logic [LENGTH-1:0] data_in_array [0:WIDTH-1];

    generate
        for (genvar i = 0; i < WIDTH; i++) begin : g_di
            assign data_in_array[i] = data_in[i*LENGTH +: LENGTH];
        end
    endgenerate

    logic [LENGTH-1:0] previous [0:WIDTH-1];
    logic [LENGTH-1:0] current  [0:WIDTH-1];

    always_ff @(posedge clk) begin
        if (rst) begin
            spikeP <= '0;
            spikeN <= '0;

            for (int i = 0; i < WIDTH; i++) begin
                previous[i] <= '0;
                current[i]  <= '0;
            end
        end else if (clk_en) begin
            spikeP <= '0;
            spikeN <= '0;

            if (sample_pulse) begin
                for (int i = 0; i < WIDTH; i++) begin
                    current[i] <= data_in_array[i];

                    if (($signed({{28{previous[i][LENGTH-1]}}, previous[i]}) - $signed({{28{data_in_array[i][LENGTH-1]}}, data_in_array[i]})) > $signed(JUMP)) begin
                        spikeN[i] <= 1'b1;
                    end

                    if (($signed({{28{data_in_array[i][LENGTH-1]}}, data_in_array[i]}) - $signed({{28{previous[i][LENGTH-1]}}, previous[i]})) > $signed(JUMP)) begin
                        spikeP[i] <= 1'b1;
                    end

                    previous[i] <= data_in_array[i];
                end
            end
        end else begin
            spikeP <= '0;
            spikeN <= '0;
        end
    end

endmodule

ASIC/rtl/temporal_mod.sv
module temporal_mod #(
    parameter WIDTH = 1,
    parameter LENGTH = 4
)(
    input  logic clk,
    input  logic rst,
    input  logic clk_en,
    input  logic sample_pulse,
    input  logic [WIDTH*LENGTH-1:0] data_in,
    input  logic [15:0] divider,
    output logic [WIDTH-1:0] spikeP,
    output logic [WIDTH-1:0] spikeN
);

    assign spikeN = {WIDTH{1'b0}};

    logic [LENGTH-1:0] data_in_array [0:WIDTH-1];

    generate
        for (genvar i = 0; i < WIDTH; i++) begin : g_data_in
            assign data_in_array[i] = data_in[i*LENGTH +: LENGTH];
        end
    endgenerate

    logic [11:0] spike_location [0:WIDTH-1];

    generate
        for (genvar i = 0; i < WIDTH; i++) begin : g_loc
            if (LENGTH == 12) begin : gen_eq12
                assign spike_location[i] = data_in_array[i];
            end else if (LENGTH < 12) begin : gen_lt12
                assign spike_location[i] = {{(12-LENGTH){1'b0}}, data_in_array[i]} << (12 - LENGTH);
            end else begin : gen_gt12
                assign spike_location[i] = data_in_array[i] >> (LENGTH - 12);
            end
        end
    endgenerate

    logic [12:0] spike_counter [0:WIDTH-1];

    always_ff @(posedge clk) begin
        if (rst) begin
            for (int i = 0; i < WIDTH; i++) begin
                spike_counter[i] <= '0;
                spikeP[i]        <= 1'b0;
            end
        end else if (clk_en) begin
            for (int i = 0; i < WIDTH; i++) begin
                if (sample_pulse) begin
                    spike_counter[i] <= '0;
                    spikeP[i]        <= 1'b0;
                end else begin
                    spike_counter[i] <= spike_counter[i] + 1'b1;
                    spikeP[i]        <= spike_counter[i] == {1'b0, spike_location[i]};
                end
            end
        end else begin
            spikeP <= '0;
        end
    end

endmodule

ASIC/rtl/rate_mod.sv
module rate_mod #(
    parameter WIDTH = 1,
    parameter LENGTH = 4
)(
    input  logic clk,
    input  logic rst,
    input  logic clk_en,
    input  logic sample_pulse,
    input  logic [WIDTH*LENGTH-1:0] data_in,
    input  logic [15:0] divider,
    output logic [WIDTH-1:0] spikeP,
    output logic [WIDTH-1:0] spikeN
);

    assign spikeN = {WIDTH{1'b0}};

    logic [LENGTH-1:0] data_in_array [0:WIDTH-1];

    generate
        for (genvar i = 0; i < WIDTH; i++) begin : g_data_in
            assign data_in_array[i] = data_in[i*LENGTH +: LENGTH];
        end
    endgenerate

    logic [LENGTH-1:0] rate_counter [0:WIDTH-1];
    logic [LENGTH-1:0] threshold [0:WIDTH-1];

    always_ff @(posedge clk) begin
        if (rst) begin
            for (int i = 0; i < WIDTH; i++) begin
                rate_counter[i] <= '0;
                threshold[i]    <= '0;
                spikeP[i]       <= 1'b0;
            end
        end else if (clk_en) begin
            for (int i = 0; i < WIDTH; i++) begin
                spikeP[i] <= 1'b0;

                if (sample_pulse) begin
                    threshold[i]    <= data_in_array[i];
                    rate_counter[i] <= '0;
                end else begin
                    rate_counter[i] <= rate_counter[i] + 1'b1;

                    if (threshold[i] != '0 &&
                        rate_counter[i] >= ((2**LENGTH - 1) - threshold[i])) begin
                        spikeP[i]       <= 1'b1;
                        rate_counter[i] <= '0;
                    end
                end
            end
        end else begin
            spikeP <= '0;
        end
    end

endmodule

ASIC/rtl/TOP_no_adc.sv
`timescale 1ns / 1ps

module TOP_no_adc #(
    parameter int WIDTH = 1,
    parameter int LENGTH = 4,
    parameter int MAX_SPIKES = 16,
    parameter int JUMP = 5,

    parameter int ADC_DIV = 62500,
    parameter int ADC_COMP_DELAY = 15625
)(
    input  logic clk,
    input  logic rst,
    input  logic [1:0] encoding_select,

    input  logic [WIDTH*LENGTH-1:0] adc_data_in,
    input  logic adc_valid,

    output logic [WIDTH-1:0] spikeP,
    output logic [WIDTH-1:0] spikeN
);

    localparam int CNT_WIDTH = $clog2(ADC_DIV);

    logic adc_clk;
    logic adc_clk_comp;
    logic sample_pulse;

    logic [CNT_WIDTH-1:0] adc_cnt;

    logic adc_valid_d;
    logic adc_rst;

    logic [WIDTH*LENGTH-1:0] adc_sample;

    always_ff @(posedge clk) begin
        if (rst) begin
            adc_valid_d  <= 1'b0;
            sample_pulse <= 1'b0;
            adc_rst <= 1'b0;
            adc_sample   <= '0;
        end else begin
            adc_valid_d  <= adc_valid;

            sample_pulse <= 1'b0;
            adc_rst <= 1'b0;

            if (adc_valid & ~adc_valid_d) begin
                adc_sample   <= adc_data_in;
                sample_pulse <= 1'b1;
            end

            if (sample_pulse) begin
                adc_rst <= 1'b1;
            end
        end
    end

    always_ff @(posedge clk) begin
        if (rst) begin
            adc_cnt      <= '0;
            adc_clk      <= 1'b0;
            adc_clk_comp <= 1'b0;
        end else begin
            if (adc_cnt == CNT_WIDTH'(ADC_DIV - 1)) begin
                adc_cnt <= '0;
            end else begin
                adc_cnt <= adc_cnt + 1'b1;
            end

            adc_clk <= adc_cnt < CNT_WIDTH'(ADC_DIV / 2);

            if (adc_cnt >= CNT_WIDTH'(ADC_COMP_DELAY)) begin
                adc_clk_comp <= (adc_cnt - CNT_WIDTH'(ADC_COMP_DELAY)) < CNT_WIDTH'(ADC_DIV / 2);
            end else begin
                adc_clk_comp <= (adc_cnt + CNT_WIDTH'(ADC_DIV - ADC_COMP_DELAY)) < CNT_WIDTH'(ADC_DIV / 2);
            end
        end
    end


    logic [WIDTH-1:0] spikeP_rate;
    logic [WIDTH-1:0] spikeN_rate;
    logic [WIDTH-1:0] spikeP_temporal;
    logic [WIDTH-1:0] spikeN_temporal;
    logic [WIDTH-1:0] spikeP_delta;
    logic [WIDTH-1:0] spikeN_delta;
    logic [WIDTH-1:0] spikeP_multispike;
    logic [WIDTH-1:0] spikeN_multispike;

    logic [3:0] clk_en;

    rate_mod #(
        .WIDTH(WIDTH),
        .LENGTH(LENGTH)
    ) rate_encoder (
        .clk(clk),
        .rst(rst),
        .clk_en(clk_en[0]),
        .sample_pulse(sample_pulse),
        .data_in(adc_sample),
        .divider(ADC_DIV[15:0]),
        .spikeP(spikeP_rate),
        .spikeN(spikeN_rate)
    );

    temporal_mod #(
        .WIDTH(WIDTH),
        .LENGTH(LENGTH)
    ) temporal_encoder (
        .clk(clk),
        .rst(rst),
        .clk_en(clk_en[1]),
        .sample_pulse(sample_pulse),
        .data_in(adc_sample),
        .divider(ADC_DIV[15:0]),
        .spikeP(spikeP_temporal),
        .spikeN(spikeN_temporal)
    );

    delta_mod #(
        .WIDTH(WIDTH),
        .LENGTH(LENGTH),
        .JUMP(JUMP)
    ) delta_encoder (
        .clk(clk),
        .rst(rst),
        .clk_en(clk_en[2]),
        .sample_pulse(sample_pulse),
        .data_in(adc_sample),
        .divider(ADC_DIV[15:0]),
        .spikeP(spikeP_delta),
        .spikeN(spikeN_delta)
    );

    multispike_mod #(
        .WIDTH(WIDTH),
        .LENGTH(LENGTH),
        .MAX_SPIKES(MAX_SPIKES)
    ) multispike_encoder (
        .clk(clk),
        .rst(rst),
        .clk_en(clk_en[3]),
        .sample_pulse(sample_pulse),
        .data_in(adc_sample),
        .divider(ADC_DIV[15:0]),
        .spikeP(spikeP_multispike),
        .spikeN(spikeN_multispike)
    );

    always_comb begin
        clk_en = 4'b0000;

        spikeP = '0;
        spikeN = '0;

        unique case (encoding_select)
            2'b00: begin
                spikeP = spikeP_rate;
                spikeN = spikeN_rate;
                clk_en[0] = 1'b1;
            end

            2'b01: begin
                spikeP = spikeP_temporal;
                spikeN = spikeN_temporal;
                clk_en[1] = 1'b1;
            end

            2'b10: begin
                spikeP = spikeP_delta;
                spikeN = spikeN_delta;
                clk_en[2] = 1'b1;
            end

            default: begin
                spikeP = spikeP_multispike;
                spikeN = spikeN_multispike;
                clk_en[3] = 1'b1;
            end
        endcase
    end

endmodule

ASIC/sim/TOP_no_adc/TOP_no_adc_tb.sv
`timescale 1ns / 1ps

module TOP_no_adc_tb;

    localparam int WIDTH = 1;
    localparam int LENGTH = 4;
    localparam int MAX_SPIKES = 16;
    localparam int JUMP = 5;

    localparam int ADC_DIV = 32;
    localparam int ADC_COMP_DELAY = 8;

    logic clk;
    logic rst;
    logic adc_valid;
    logic [1:0] encoding_select;
    logic [WIDTH*LENGTH-1:0] adc_data_in;
    logic [WIDTH-1:0] spikeP;
    logic [WIDTH-1:0] spikeN;

    TOP_no_adc #(
        .WIDTH(WIDTH),
        .LENGTH(LENGTH),
        .MAX_SPIKES(MAX_SPIKES),
        .JUMP(JUMP),
        .ADC_DIV(ADC_DIV),
        .ADC_COMP_DELAY(ADC_COMP_DELAY)
    ) dut (
        .clk(clk),
        .rst(rst),
        .encoding_select(encoding_select),
        .adc_data_in(adc_data_in),
        .adc_valid(adc_valid),
        .spikeP(spikeP),
        .spikeN(spikeN)
    );

    always #5 clk = ~clk; // 100 mhz

    initial begin
        clk = 1'b0;
        rst = 1'b1;
        adc_valid = 1'b0;
        encoding_select = 2'b00;
        adc_data_in = 4'd0;

        repeat (5) @(posedge clk);
        rst = 1'b0;

        encoding_select = 2'b00;
        run_adc_ramp();

        encoding_select = 2'b01;
        run_adc_ramp();

        encoding_select = 2'b10;
        run_adc_ramp();

        encoding_select = 2'b11;
        run_adc_ramp();

        repeat (100) @(posedge clk);
        $finish;
    end

    task automatic pulse_adc_valid;
        begin
            adc_valid = 1'b1;
            @(posedge clk);
            adc_valid = 1'b0;
        end
    endtask

    task automatic run_adc_ramp;
        begin
            for (int value = 0; value < 16; value++) begin
                adc_data_in = value[3:0];

                // adc result becomes valid once per conversion frame
                repeat (ADC_DIV - 1) @(posedge clk);
                pulse_adc_valid();
            end
        end
    endtask

    initial begin
        $dumpfile("TOP_no_adc_tb.vcd");
        $dumpvars(0, TOP_no_adc_tb);
    end

endmodule

ASIC/sim/TOP_no_adc/TOP_no_adc_tb.vcd
$version Generated by VerilatedVcd $end
$timescale 1ps $end
 $scope module $rootio $end
 $upscope $end
 $scope module TOP_no_adc_tb $end
  $var wire 32 Q WIDTH [31:0] $end
  $var wire 32 R LENGTH [31:0] $end
  $var wire 32 S MAX_SPIKES [31:0] $end
  $var wire 32 T JUMP [31:0] $end
  $var wire 32 U ADC_DIV [31:0] $end
  $var wire 32 V ADC_COMP_DELAY [31:0] $end
  $var wire 1 L clk $end
  $var wire 1 M rst $end
  $var wire 1 N adc_valid $end
  $var wire 2 O encoding_select [1:0] $end
  $var wire 4 P adc_data_in [3:0] $end
  $var wire 1 # spikeP [0:0] $end
  $var wire 1 $ spikeN [0:0] $end
  $scope module dut $end
   $var wire 32 Q WIDTH [31:0] $end
   $var wire 32 R LENGTH [31:0] $end
   $var wire 32 S MAX_SPIKES [31:0] $end
   $var wire 32 T JUMP [31:0] $end
   $var wire 32 U ADC_DIV [31:0] $end
   $var wire 32 V ADC_COMP_DELAY [31:0] $end
   $var wire 1 L clk $end
   $var wire 1 M rst $end
   $var wire 2 O encoding_select [1:0] $end
   $var wire 4 P adc_data_in [3:0] $end
   $var wire 1 N adc_valid $end
   $var wire 1 # spikeP [0:0] $end
   $var wire 1 $ spikeN [0:0] $end
   $var wire 32 T CNT_WIDTH [31:0] $end
   $var wire 1 * adc_clk $end
   $var wire 1 + adc_clk_comp $end
   $var wire 1 , sample_pulse $end
   $var wire 5 - adc_cnt [4:0] $end
   $var wire 1 . adc_valid_d $end
   $var wire 1 / adc_rst $end
   $var wire 4 0 adc_sample [3:0] $end
   $var wire 1 1 spikeP_rate [0:0] $end
   $var wire 1 W spikeN_rate [0:0] $end
   $var wire 1 2 spikeP_temporal [0:0] $end
   $var wire 1 W spikeN_temporal [0:0] $end
   $var wire 1 3 spikeP_delta [0:0] $end
   $var wire 1 4 spikeN_delta [0:0] $end
   $var wire 1 5 spikeP_multispike [0:0] $end
   $var wire 1 W spikeN_multispike [0:0] $end
   $var wire 4 % clk_en [3:0] $end
   $scope module delta_encoder $end
    $var wire 32 Q WIDTH [31:0] $end
    $var wire 32 R LENGTH [31:0] $end
    $var wire 32 T JUMP [31:0] $end
    $var wire 1 L clk $end
    $var wire 1 M rst $end
    $var wire 1 & clk_en $end
    $var wire 1 , sample_pulse $end
    $var wire 4 0 data_in [3:0] $end
    $var wire 16 X divider [15:0] $end
    $var wire 1 3 spikeP [0:0] $end
    $var wire 1 4 spikeN [0:0] $end
    $var wire 4 6 data_in_array[0] [3:0] $end
    $var wire 4 7 previous[0] [3:0] $end
    $var wire 4 8 current[0] [3:0] $end
    $scope module unnamedblk1 $end
     $var wire 32 9 i [31:0] $end
    $upscope $end
    $scope module unnamedblk2 $end
     $var wire 32 : i [31:0] $end
    $upscope $end
   $upscope $end
   $scope module multispike_encoder $end
    $var wire 32 Y WIDTH [31:0] $end
    $var wire 32 Z LENGTH [31:0] $end
    $var wire 32 [ MAX_SPIKES [31:0] $end
    $var wire 1 L clk $end
    $var wire 1 M rst $end
    $var wire 1 ' clk_en $end
    $var wire 1 , sample_pulse $end
    $var wire 4 0 data_in[0] [3:0] $end
    $var wire 16 X divider [15:0] $end
    $var wire 1 5 spikeP [0:0] $end
    $var wire 1 W spikeN [0:0] $end
    $var wire 32 \ SPIKE_BITS [31:0] $end
    $var wire 5 ; num_spikes[0] [4:0] $end
    $var wire 5 < spike_count[0] [4:0] $end
    $var wire 16 = spike_interval[0] [15:0] $end
    $var wire 16 > interval_counter[0] [15:0] $end
    $var wire 5 ? temp_spikes[0] [4:0] $end
    $scope module unnamedblk1 $end
     $var wire 32 @ i [31:0] $end
    $upscope $end
    $scope module unnamedblk2 $end
     $var wire 32 A i [31:0] $end
    $upscope $end
   $upscope $end
   $scope module rate_encoder $end
    $var wire 32 Y WIDTH [31:0] $end
    $var wire 32 Z LENGTH [31:0] $end
    $var wire 1 L clk $end
    $var wire 1 M rst $end
    $var wire 1 ( clk_en $end
    $var wire 1 , sample_pulse $end
    $var wire 4 0 data_in [3:0] $end
    $var wire 16 X divider [15:0] $end
    $var wire 1 1 spikeP [0:0] $end
    $var wire 1 W spikeN [0:0] $end
    $var wire 4 B data_in_array[0] [3:0] $end
    $var wire 4 C rate_counter[0] [3:0] $end
    $var wire 4 D threshold[0] [3:0] $end
    $scope module unnamedblk1 $end
     $var wire 32 E i [31:0] $end
    $upscope $end
    $scope module unnamedblk2 $end
     $var wire 32 F i [31:0] $end
    $upscope $end
   $upscope $end
   $scope module temporal_encoder $end
    $var wire 32 Y WIDTH [31:0] $end
    $var wire 32 Z LENGTH [31:0] $end
    $var wire 1 L clk $end
    $var wire 1 M rst $end
    $var wire 1 ) clk_en $end
    $var wire 1 , sample_pulse $end
    $var wire 4 0 data_in [3:0] $end
    $var wire 16 X divider [15:0] $end
    $var wire 1 2 spikeP [0:0] $end
    $var wire 1 W spikeN [0:0] $end
    $var wire 4 G data_in_array[0] [3:0] $end
    $var wire 12 H spike_location[0] [11:0] $end
    $var wire 13 I spike_counter[0] [12:0] $end
    $scope module unnamedblk1 $end
     $var wire 32 J i [31:0] $end
    $upscope $end
    $scope module unnamedblk2 $end
     $var wire 32 K i [31:0] $end
    $upscope $end
   $upscope $end
  $upscope $end
 $upscope $end
$enddefinitions $end


#0
0#
0$
b0001 %
0&
0'
1(
0)
0*
0+
0,
b00000 -
0.
0/
b0000 0
01
02
03
04
05
b0000 6
b0000 7
b0000 8
b00000000000000000000000000000000 9
b00000000000000000000000000000000 :
b00000 ;
b00000 <
b0000000000000000 =
b0000000000000000 >
b00000 ?
b00000000000000000000000000000000 @
b00000000000000000000000000000000 A
b0000 B
b0000 C
b0000 D
b00000000000000000000000000000000 E
b00000000000000000000000000000000 F
b0000 G
b000000000000 H
b0000000000000 I
b00000000000000000000000000000000 J
b00000000000000000000000000000000 K
0L
1M
0N
b00 O
b0000 P
b00000000000000000000000000000001 Q
b00000000000000000000000000000100 R
b00000000000000000000000000010000 S
b00000000000000000000000000000101 T
b00000000000000000000000000100000 U
b00000000000000000000000000001000 V
0W
b0000000000100000 X
b00000000000000000000000000000001 Y
b00000000000000000000000000000100 Z
b00000000000000000000000000010000 [
b00000000000000000000000000000101 \
#5000
b00000000000000000000000000000001 9
b1111111111111111 =
b00000000000000000000000000000001 @
b00000000000000000000000000000001 E
b00000000000000000000000000000001 J
1L
#10000
0L
#15000
1L
#20000
0L
#25000
1L
#30000
0L
#35000
1L
#40000
0L
#45000
1*
b00001 -
b0001 C
b00000000000000000000000000000001 F
1L
0M
#50000
0L
#55000
b00010 -
b0010 C
1L
#60000
0L
#65000
b00011 -
b0011 C
1L
#70000
0L
#75000
b00100 -
b0100 C
1L
#80000
0L
#85000
b00101 -
b0101 C
1L
#90000
0L
#95000
b00110 -
b0110 C
1L
#100000
0L
#105000
b00111 -
b0111 C
1L
#110000
0L
#115000
b01000 -
b1000 C
1L
#120000
0L
#125000
1+
b01001 -
b1001 C
1L
#130000
0L
#135000
b01010 -
b1010 C
1L
#140000
0L
#145000
b01011 -
b1011 C
1L
#150000
0L
#155000
b01100 -
b1100 C
1L
#160000
0L
#165000
b01101 -
b1101 C
1L
#170000
0L
#175000
b01110 -
b1110 C
1L
#180000
0L
#185000
b01111 -
b1111 C
1L
#190000
0L
#195000
b10000 -
b0000 C
1L
#200000
0L
#205000
0*
b10001 -
b0001 C
1L
#210000
0L
#215000
b10010 -
b0010 C
1L
#220000
0L
#225000
b10011 -
b0011 C
1L
#230000
0L
#235000
b10100 -
b0100 C
1L
#240000
0L
#245000
b10101 -
b0101 C
1L
#250000
0L
#255000
b10110 -
b0110 C
1L
#260000
0L
#265000
b10111 -
b0111 C
1L
#270000
0L
#275000
b11000 -
b1000 C
1L
#280000
0L
#285000
0+
b11001 -
b1001 C
1L
#290000
0L
#295000
b11010 -
b1010 C
1L
#300000
0L
#305000
b11011 -
b1011 C
1L
#310000
0L
#315000
b11100 -
b1100 C
1L
#320000
0L
#325000
b11101 -
b1101 C
1L
#330000
0L
#335000
b11110 -
b1110 C
1L
#340000
0L
#345000
b11111 -
b1111 C
1L
#350000
0L
#355000
1,
b00000 -
1.
b0000 C
1L
1N
#360000
0L
#365000
1*
0,
b00001 -
0.
1/
1L
0N
b0001 P
#370000
0L
#375000
b00010 -
0/
b0001 C
1L
#380000
0L
#385000
b00011 -
b0010 C
1L
#390000
0L
#395000
b00100 -
b0011 C
1L
#400000
0L
#405000
b00101 -
b0100 C
1L
#410000
0L
#415000
b00110 -
b0101 C
1L
#420000
0L
#425000
b00111 -
b0110 C
1L
#430000
0L
#435000
b01000 -
b0111 C
1L
#440000
0L
#445000
1+
b01001 -
b1000 C
1L
#450000
0L
#455000
b01010 -
b1001 C
1L
#460000
0L
#465000
b01011 -
b1010 C
1L
#470000
0L
#475000
b01100 -
b1011 C
1L
#480000
0L
#485000
b01101 -
b1100 C
1L
#490000
0L
#495000
b01110 -
b1101 C
1L
#500000
0L
#505000
b01111 -
b1110 C
1L
#510000
0L
#515000
b10000 -
b1111 C
1L
#520000
0L
#525000
0*
b10001 -
b0000 C
1L
#530000
0L
#535000
b10010 -
b0001 C
1L
#540000
0L
#545000
b10011 -
b0010 C
1L
#550000
0L
#555000
b10100 -
b0011 C
1L
#560000
0L
#565000
b10101 -
b0100 C
1L
#570000
0L
#575000
b10110 -
b0101 C
1L
#580000
0L
#585000
b10111 -
b0110 C
1L
#590000
0L
#595000
b11000 -
b0111 C
1L
#600000
0L
#605000
0+
b11001 -
b1000 C
1L
#610000
0L
#615000
b11010 -
b1001 C
1L
#620000
0L
#625000
b11011 -
b1010 C
1L
#630000
0L
#635000
b11100 -
b1011 C
1L
#640000
0L
#645000
b11101 -
b1100 C
1L
#650000
0L
#655000
b11110 -
b1101 C
1L
#660000
0L
#665000
b11111 -
b1110 C
1L
#670000
0L
#675000
1,
b00000 -
1.
b0001 0
b0001 6
b0001 B
b1111 C
b0001 G
b000100000000 H
1L
1N
#680000
0L
#685000
1*
0,
b00001 -
0.
1/
b0000 C
b0001 D
1L
0N
b0010 P
#690000
0L
#695000
b00010 -
0/
b0001 C
1L
#700000
0L
#705000
b00011 -
b0010 C
1L
#710000
0L
#715000
b00100 -
b0011 C
1L
#720000
0L
#725000
b00101 -
b0100 C
1L
#730000
0L
#735000
b00110 -
b0101 C
1L
#740000
0L
#745000
b00111 -
b0110 C
1L
#750000
0L
#755000
b01000 -
b0111 C
1L
#760000
0L
#765000
1+
b01001 -
b1000 C
1L
#770000
0L
#775000
b01010 -
b1001 C
1L
#780000
0L
#785000
b01011 -
b1010 C
1L
#790000
0L
#795000
b01100 -
b1011 C
1L
#800000
0L
#805000
b01101 -
b1100 C
1L
#810000
0L
#815000
b01110 -
b1101 C
1L
#820000
0L
#825000
b01111 -
b1110 C
1L
#830000
0L
#835000
1#
b10000 -
11
b0000 C
1L
#840000
0L
#845000
0#
0*
b10001 -
01
b0001 C
1L
#850000
0L
#855000
b10010 -
b0010 C
1L
#860000
0L
#865000
b10011 -
b0011 C
1L
#870000
0L
#875000
b10100 -
b0100 C
1L
#880000
0L
#885000
b10101 -
b0101 C
1L
#890000
0L
#895000
b10110 -
b0110 C
1L
#900000
0L
#905000
b10111 -
b0111 C
1L
#910000
0L
#915000
b11000 -
b1000 C
1L
#920000
0L
#925000
0+
b11001 -
b1001 C
1L
#930000
0L
#935000
b11010 -
b1010 C
1L
#940000
0L
#945000
b11011 -
b1011 C
1L
#950000
0L
#955000
b11100 -
b1100 C
1L
#960000
0L
#965000
b11101 -
b1101 C
1L
#970000
0L
#975000
b11110 -
b1110 C
1L
#980000
0L
#985000
1#
b11111 -
11
b0000 C
1L
#990000
0L
#995000
0#
1,
b00000 -
1.
b0010 0
01
b0010 6
b0010 B
b0001 C
b0010 G
b001000000000 H
1L
1N
#1000000
0L
#1005000
1*
0,
b00001 -
0.
1/
b0000 C
b0010 D
1L
0N
b0011 P
#1010000
0L
#1015000
b00010 -
0/
b0001 C
1L
#1020000
0L
#1025000
b00011 -
b0010 C
1L
#1030000
0L
#1035000
b00100 -
b0011 C
1L
#1040000
0L
#1045000
b00101 -
b0100 C
1L
#1050000
0L
#1055000
b00110 -
b0101 C
1L
#1060000
0L
#1065000
b00111 -
b0110 C
1L
#1070000
0L
#1075000
b01000 -
b0111 C
1L
#1080000
0L
#1085000
1+
b01001 -
b1000 C
1L
#1090000
0L
#1095000
b01010 -
b1001 C
1L
#1100000
0L
#1105000
b01011 -
b1010 C
1L
#1110000
0L
#1115000
b01100 -
b1011 C
1L
#1120000
0L
#1125000
b01101 -
b1100 C
1L
#1130000
0L
#1135000
b01110 -
b1101 C
1L
#1140000
0L
#1145000
1#
b01111 -
11
b0000 C
1L
#1150000
0L
#1155000
0#
b10000 -
01
b0001 C
1L
#1160000
0L
#1165000
0*
b10001 -
b0010 C
1L
#1170000
0L
#1175000
b10010 -
b0011 C
1L
#1180000
0L
#1185000
b10011 -
b0100 C
1L
#1190000
0L
#1195000
b10100 -
b0101 C
1L
#1200000
0L
#1205000
b10101 -
b0110 C
1L
#1210000
0L
#1215000
b10110 -
b0111 C
1L
#1220000
0L
#1225000
b10111 -
b1000 C
1L
#1230000
0L
#1235000
b11000 -
b1001 C
1L
#1240000
0L
#1245000
0+
b11001 -
b1010 C
1L
#1250000
0L
#1255000
b11010 -
b1011 C
1L
#1260000
0L
#1265000
b11011 -
b1100 C
1L
#1270000
0L
#1275000
b11100 -
b1101 C
1L
#1280000
0L
#1285000
1#
b11101 -
11
b0000 C
1L
#1290000
0L
#1295000
0#
b11110 -
01
b0001 C
1L
#1300000
0L
#1305000
b11111 -
b0010 C
1L
#1310000
0L
#1315000
1,
b00000 -
1.
b0011 0
b0011 6
b0011 B
b0011 C
b0011 G
b001100000000 H
1L
1N
#1320000
0L
#1325000
1*
0,
b00001 -
0.
1/
b0000 C
b0011 D
1L
0N
b0100 P
#1330000
0L
#1335000
b00010 -
0/
b0001 C
1L
#1340000
0L
#1345000
b00011 -
b0010 C
1L
#1350000
0L
#1355000
b00100 -
b0011 C
1L
#1360000
0L
#1365000
b00101 -
b0100 C
1L
#1370000
0L
#1375000
b00110 -
b0101 C
1L
#1380000
0L
#1385000
b00111 -
b0110 C
1L
#1390000
0L
#1395000
b01000 -
b0111 C
1L
#1400000
0L
#1405000
1+
b01001 -
b1000 C
1L
#1410000
0L
#1415000
b01010 -
b1001 C
1L
#1420000
0L
#1425000
b01011 -
b1010 C
1L
#1430000
0L
#1435000
b01100 -
b1011 C
1L
#1440000
0L
#1445000
b01101 -
b1100 C
1L
#1450000
0L
#1455000
1#
b01110 -
11
b0000 C
1L
#1460000
0L
#1465000
0#
b01111 -
01
b0001 C
1L
#1470000
0L
#1475000
b10000 -
b0010 C
1L
#1480000
0L
#1485000
0*
b10001 -
b0011 C
1L
#1490000
0L
#1495000
b10010 -
b0100 C
1L
#1500000
0L
#1505000
b10011 -
b0101 C
1L
#1510000
0L
#1515000
b10100 -
b0110 C
1L
#1520000
0L
#1525000
b10101 -
b0111 C
1L
#1530000
0L
#1535000
b10110 -
b1000 C
1L
#1540000
0L
#1545000
b10111 -
b1001 C
1L
#1550000
0L
#1555000
b11000 -
b1010 C
1L
#1560000
0L
#1565000
0+
b11001 -
b1011 C
1L
#1570000
0L
#1575000
b11010 -
b1100 C
1L
#1580000
0L
#1585000
1#
b11011 -
11
b0000 C
1L
#1590000
0L
#1595000
0#
b11100 -
01
b0001 C
1L
#1600000
0L
#1605000
b11101 -
b0010 C
1L
#1610000
0L
#1615000
b11110 -
b0011 C
1L
#1620000
0L
#1625000
b11111 -
b0100 C
1L
#1630000
0L
#1635000
1,
b00000 -
1.
b0100 0
b0100 6
b0100 B
b0101 C
b0100 G
b010000000000 H
1L
1N
#1640000
0L
#1645000
1*
0,
b00001 -
0.
1/
b0000 C
b0100 D
1L
0N
b0101 P
#1650000
0L
#1655000
b00010 -
0/
b0001 C
1L
#1660000
0L
#1665000
b00011 -
b0010 C
1L
#1670000
0L
#1675000
b00100 -
b0011 C
1L
#1680000
0L
#1685000
b00101 -
b0100 C
1L
#1690000
0L
#1695000
b00110 -
b0101 C
1L
#1700000
0L
#1705000
b00111 -
b0110 C
1L
#1710000
0L
#1715000
b01000 -
b0111 C
1L
#1720000
0L
#1725000
1+
b01001 -
b1000 C
1L
#1730000
0L
