ASIC/rtl/multispike_mod.sv
`timescale 1ns / 1ps

module multispike_mod #(
    parameter WIDTH = 1,
    parameter LENGTH = 12,
    parameter MAX_SPIKES = 16
)(
    input  logic clk,
    input  logic rst,
    input  logic clk_en,
    input  logic sample_pulse,
    input  logic [WIDTH-1:0][LENGTH-1:0] data_in,
    input  logic [15:0] divider,
    output logic [WIDTH-1:0] spikeP,
    output logic [WIDTH-1:0] spikeN
);

    assign spikeN = '0;

    localparam SPIKE_BITS = $clog2(MAX_SPIKES + 1);

    logic [WIDTH-1:0][SPIKE_BITS-1:0] num_spikes;
    logic [WIDTH-1:0][SPIKE_BITS-1:0] spike_count;
    logic [WIDTH-1:0][15:0] spike_interval;
    logic [WIDTH-1:0][15:0] interval_counter;
    logic [WIDTH-1:0][SPIKE_BITS-1:0] temp_spikes;

    always_ff @(posedge clk) begin
        if (rst) begin
            for (int i = 0; i < WIDTH; i++) begin
                num_spikes[i]       <= '0;
                spike_count[i]      <= '0;
                spike_interval[i]   <= '1;
                interval_counter[i] <= '0;
                spikeP[i]           <= 1'b0;
                temp_spikes[i]      <= '0;
            end
        end else if (clk_en) begin
            for (int i = 0; i < WIDTH; i++) begin
                if (sample_pulse) begin
                    temp_spikes[i] <= (data_in[i] * MAX_SPIKES) >> LENGTH;
                    num_spikes[i]  <= (data_in[i] * MAX_SPIKES) >> LENGTH;

                    if (((data_in[i] * MAX_SPIKES) >> LENGTH) == 0) begin
                        spike_interval[i] <= 16'hFFFF;
                    end else begin
                        // spike_interval = divider / num_spikes
                        spike_interval[i] <= (divider) / ((data_in[i] * MAX_SPIKES) >> LENGTH);
                    end

                    spike_count[i]      <= '0;
                    interval_counter[i] <= '0;
                    spikeP[i]           <= 1'b0;
                end else begin
                    interval_counter[i] <= interval_counter[i] + 1'b1;

                    if (
                        spike_count[i] < num_spikes[i] &&
                        interval_counter[i] >= spike_interval[i]
                    ) begin
                        spikeP[i]           <= 1'b1;
                        spike_count[i]      <= spike_count[i] + 1'b1;
                        interval_counter[i] <= '0;
                    end else begin
                        spikeP[i] <= 1'b0;
                    end
                end
            end
        end else begin
            spikeP <= '0;
        end
    end

endmodule

ASIC/rtl/delta_mod.sv
module delta_mod #(
    parameter int WIDTH = 1,
    parameter int LENGTH = 4,
    parameter int JUMP = 5
)(
    input  logic clk,
    input  logic rst,
    input  logic clk_en,
    input  logic sample_pulse,
    input  logic [WIDTH*LENGTH-1:0] data_in,
    input  logic [15:0] divider,
    output logic [WIDTH-1:0] spikeP,
    output logic [WIDTH-1:0] spikeN
);

    logic [LENGTH-1:0] data_in_array [0:WIDTH-1];

    generate
        for (genvar i = 0; i < WIDTH; i++) begin : g_di
            assign data_in_array[i] = data_in[i*LENGTH +: LENGTH];
        end
    endgenerate

    logic [LENGTH-1:0] previous [0:WIDTH-1];
    logic [LENGTH-1:0] current  [0:WIDTH-1];

    always_ff @(posedge clk) begin
        if (rst) begin
            spikeP <= '0;
            spikeN <= '0;

            for (int i = 0; i < WIDTH; i++) begin
                previous[i] <= '0;
                current[i]  <= '0;
            end
        end else if (clk_en) begin
            spikeP <= '0;
            spikeN <= '0;

            if (sample_pulse) begin
                for (int i = 0; i < WIDTH; i++) begin
                    current[i] <= data_in_array[i];

                    if (($signed({{28{previous[i][LENGTH-1]}}, previous[i]}) - $signed({{28{data_in_array[i][LENGTH-1]}}, data_in_array[i]})) > $signed(JUMP)) begin
                        spikeN[i] <= 1'b1;
                    end

                    if (($signed({{28{data_in_array[i][LENGTH-1]}}, data_in_array[i]}) - $signed({{28{previous[i][LENGTH-1]}}, previous[i]})) > $signed(JUMP)) begin
                        spikeP[i] <= 1'b1;
                    end

                    previous[i] <= data_in_array[i];
                end
            end
        end else begin
            spikeP <= '0;
            spikeN <= '0;
        end
    end

endmodule

ASIC/rtl/temporal_mod.sv
module temporal_mod #(
    parameter WIDTH = 1,
    parameter LENGTH = 12
)(
    input  logic clk,
    input  logic rst,
    input  logic clk_en,
    input  logic sample_pulse,
    input  logic [WIDTH*LENGTH-1:0] data_in,
    input  logic [15:0] divider,
    output logic [WIDTH-1:0] spikeP,
    output logic [WIDTH-1:0] spikeN
);

    assign spikeN = {WIDTH{1'b0}};

    logic [LENGTH-1:0] data_in_array [0:WIDTH-1];

    generate
        for (genvar i = 0; i < WIDTH; i++) begin : g_data_in
            assign data_in_array[i] = data_in[i*LENGTH +: LENGTH];
        end
    endgenerate

    logic [15:0] spike_location [0:WIDTH-1];
    logic [15:0] spike_counter [0:WIDTH-1];
    logic [31:0] location_calc [0:WIDTH-1];

    generate
        for (genvar i = 0; i < WIDTH; i++) begin : g_loc
            // Calculate spike location: (data_in * divider) >> LENGTH
            assign location_calc[i] = (({28'h0, data_in_array[i]} * {16'h0, divider[15:0]}) >> LENGTH);
        end
    endgenerate

    always_ff @(posedge clk) begin
        if (rst) begin
            for (int i = 0; i < WIDTH; i++) begin
                spike_counter[i] <= '0;
                spikeP[i]        <= 1'b0;
                spike_location[i] <= '0;
            end
        end else if (clk_en) begin
            for (int i = 0; i < WIDTH; i++) begin
                if (sample_pulse) begin
                    spike_counter[i] <= '0;
                    spike_location[i] <= location_calc[i][15:0];
                    spikeP[i]        <= (location_calc[i][15:0] == 16'h0000);
                end else begin
                    spike_counter[i] <= spike_counter[i] + 1'b1;
                    spikeP[i]        <= (spike_counter[i] + 1'b1 == spike_location[i]);
                end
            end
        end else begin
            spikeP <= '0;
        end
    end

endmodule

ASIC/rtl/rate_mod.sv
module rate_mod #(
    parameter WIDTH = 1,
    parameter LENGTH = 4
)(
    input  logic clk,
    input  logic rst,
    input  logic clk_en,
    input  logic sample_pulse,
    input  logic [WIDTH*LENGTH-1:0] data_in,
    input  logic [15:0] divider,
    output logic [WIDTH-1:0] spikeP,
    output logic [WIDTH-1:0] spikeN
);

    assign spikeN = {WIDTH{1'b0}};

    logic [LENGTH-1:0] data_in_array [0:WIDTH-1];

    generate
        for (genvar i = 0; i < WIDTH; i++) begin : g_data_in
            assign data_in_array[i] = data_in[i*LENGTH +: LENGTH];
        end
    endgenerate

    logic [LENGTH-1:0] rate_counter [0:WIDTH-1];
    logic [LENGTH-1:0] threshold [0:WIDTH-1];

    always_ff @(posedge clk) begin
        if (rst) begin
            for (int i = 0; i < WIDTH; i++) begin
                rate_counter[i] <= '0;
                threshold[i]    <= '0;
                spikeP[i]       <= 1'b0;
            end
        end else if (clk_en) begin
            for (int i = 0; i < WIDTH; i++) begin
                spikeP[i] <= 1'b0;

                if (sample_pulse) begin
                    threshold[i]    <= data_in_array[i];
                    rate_counter[i] <= '0;
                end else begin
                    rate_counter[i] <= rate_counter[i] + 1'b1;

                    if (threshold[i] != '0 &&
                        rate_counter[i] >= ((2**LENGTH - 1) - threshold[i])) begin
                        spikeP[i]       <= 1'b1;
                        rate_counter[i] <= '0;
                    end
                end
            end
        end else begin
            spikeP <= '0;
        end
    end

endmodule

ASIC/rtl/TOP_no_adc.sv
`timescale 1ns / 1ps

module TOP_no_adc #(
    parameter int WIDTH = 1,
    parameter int LENGTH = 4,
    parameter int MAX_SPIKES = 16,
    parameter int JUMP = 5,

    parameter int ADC_DIV = 62500,
    parameter int ADC_COMP_DELAY = 15625
)(
    input  logic clk,
    input  logic rst,
    input  logic [1:0] encoding_select,

    input  logic [WIDTH*LENGTH-1:0] adc_data_in,
    input  logic adc_valid,

    output logic [WIDTH-1:0] spikeP,
    output logic [WIDTH-1:0] spikeN
);

    localparam int CNT_WIDTH = $clog2(ADC_DIV);

    logic adc_clk;
    logic adc_clk_comp;
    logic sample_pulse;

    logic [CNT_WIDTH-1:0] adc_cnt;

    logic adc_valid_d;
    logic adc_rst;

    logic [WIDTH*LENGTH-1:0] adc_sample;

    always_ff @(posedge clk) begin
        if (rst) begin
            adc_valid_d  <= 1'b0;
            sample_pulse <= 1'b0;
            adc_rst <= 1'b0;
            adc_sample   <= '0;
        end else begin
            adc_valid_d  <= adc_valid;

            sample_pulse <= 1'b0;
            adc_rst <= 1'b0;

            if (adc_valid & ~adc_valid_d) begin
                adc_sample   <= adc_data_in;
                sample_pulse <= 1'b1;
            end

            if (sample_pulse) begin
                adc_rst <= 1'b1;
            end
        end
    end

    always_ff @(posedge clk) begin
        if (rst) begin
            adc_cnt      <= '0;
            adc_clk      <= 1'b0;
            adc_clk_comp <= 1'b0;
        end else begin
            if (adc_cnt == CNT_WIDTH'(ADC_DIV - 1)) begin
                adc_cnt <= '0;
            end else begin
                adc_cnt <= adc_cnt + 1'b1;
            end

            adc_clk <= adc_cnt < CNT_WIDTH'(ADC_DIV / 2);

            if (adc_cnt >= CNT_WIDTH'(ADC_COMP_DELAY)) begin
                adc_clk_comp <= (adc_cnt - CNT_WIDTH'(ADC_COMP_DELAY)) < CNT_WIDTH'(ADC_DIV / 2);
            end else begin
                adc_clk_comp <= (adc_cnt + CNT_WIDTH'(ADC_DIV - ADC_COMP_DELAY)) < CNT_WIDTH'(ADC_DIV / 2);
            end
        end
    end


    logic [WIDTH-1:0] spikeP_rate;
    logic [WIDTH-1:0] spikeN_rate;
    logic [WIDTH-1:0] spikeP_temporal;
    logic [WIDTH-1:0] spikeN_temporal;
    logic [WIDTH-1:0] spikeP_delta;
    logic [WIDTH-1:0] spikeN_delta;
    logic [WIDTH-1:0] spikeP_multispike;
    logic [WIDTH-1:0] spikeN_multispike;

    logic [3:0] clk_en;

    rate_mod #(
        .WIDTH(WIDTH),
        .LENGTH(LENGTH)
    ) rate_encoder (
        .clk(clk),
        .rst(rst),
        .clk_en(clk_en[0]),
        .sample_pulse(sample_pulse),
        .data_in(adc_sample),
        .divider(ADC_DIV[15:0]),
        .spikeP(spikeP_rate),
        .spikeN(spikeN_rate)
    );

    temporal_mod #(
        .WIDTH(WIDTH),
        .LENGTH(LENGTH)
    ) temporal_encoder (
        .clk(clk),
        .rst(rst),
        .clk_en(clk_en[1]),
        .sample_pulse(sample_pulse),
        .data_in(adc_sample),
        .divider(ADC_DIV[15:0]),
        .spikeP(spikeP_temporal),
        .spikeN(spikeN_temporal)
    );

    delta_mod #(
        .WIDTH(WIDTH),
        .LENGTH(LENGTH),
        .JUMP(JUMP)
    ) delta_encoder (
        .clk(clk),
        .rst(rst),
        .clk_en(clk_en[2]),
        .sample_pulse(sample_pulse),
        .data_in(adc_sample),
        .divider(ADC_DIV[15:0]),
        .spikeP(spikeP_delta),
        .spikeN(spikeN_delta)
    );

    multispike_mod #(
        .WIDTH(WIDTH),
        .LENGTH(LENGTH),
        .MAX_SPIKES(MAX_SPIKES)
    ) multispike_encoder (
        .clk(clk),
        .rst(rst),
        .clk_en(clk_en[3]),
        .sample_pulse(sample_pulse),
        .data_in(adc_sample),
        .divider(ADC_DIV[15:0]),
        .spikeP(spikeP_multispike),
        .spikeN(spikeN_multispike)
    );

    always_comb begin
        clk_en = 4'b0000;

        spikeP = '0;
        spikeN = '0;

        unique case (encoding_select)
            2'b00: begin
                spikeP = spikeP_rate;
                spikeN = spikeN_rate;
                clk_en[0] = 1'b1;
            end

            2'b01: begin
                spikeP = spikeP_temporal;
                spikeN = spikeN_temporal;
                clk_en[1] = 1'b1;
            end

            2'b10: begin
                spikeP = spikeP_delta;
                spikeN = spikeN_delta;
                clk_en[2] = 1'b1;
            end

            default: begin
                spikeP = spikeP_multispike;
                spikeN = spikeN_multispike;
                clk_en[3] = 1'b1;
            end
        endcase
    end

endmodule

ASIC/sim/TOP_no_adc/TOP_no_adc_tb.sv
`timescale 1ns / 1ps

module TOP_no_adc_tb;

    localparam int WIDTH = 1;
    localparam int LENGTH = 4;
    localparam int MAX_SPIKES = 16;
    localparam int JUMP = 5;

    localparam int ADC_DIV = 500;  // Match 500-cycle sample period
    localparam int ADC_COMP_DELAY = 8;

    logic clk;
    logic rst;
    logic adc_valid;
    logic [1:0] encoding_select;
    logic [WIDTH*LENGTH-1:0] adc_data_in;
    logic [WIDTH-1:0] spikeP;
    logic [WIDTH-1:0] spikeN;

    int spike_count_p;
    int spike_count_n;

    TOP_no_adc #(
        .WIDTH(WIDTH),
        .LENGTH(LENGTH),
        .MAX_SPIKES(MAX_SPIKES),
        .JUMP(JUMP),
        .ADC_DIV(ADC_DIV),
        .ADC_COMP_DELAY(ADC_COMP_DELAY)
    ) dut (
        .clk(clk),
        .rst(rst),
        .encoding_select(encoding_select),
        .adc_data_in(adc_data_in),
        .adc_valid(adc_valid),
        .spikeP(spikeP),
        .spikeN(spikeN)
    );

    always #5 clk = ~clk; // 100 mhz

    initial begin
        clk = 1'b0;
        rst = 1'b1;
        adc_valid = 1'b0;
        encoding_select = 2'b00;
        adc_data_in = 4'd0;
        spike_count_p = 0;
        spike_count_n = 0;

        repeat (5) @(posedge clk);
        rst = 1'b0;

        // Test 1: Rate encoding - ramp 0-15
        $display("[%t] Test 1: Rate Encoding", $time);
        encoding_select = 2'b00;
        spike_count_p = 0;
        spike_count_n = 0;
        run_adc_ramp(0, 15, 1);
        $display("[%t] Rate Encoding: Generated %0d spikeP, %0d spikeN", $time, spike_count_p, spike_count_n);

        // Test 2: Temporal encoding - ramp 0-15
        $display("[%t] Test 2: Temporal Encoding", $time);
        encoding_select = 2'b01;
        spike_count_p = 0;
        spike_count_n = 0;
        run_adc_ramp(0, 15, 1);
        $display("[%t] Temporal Encoding: Generated %0d spikeP, %0d spikeN", $time, spike_count_p, spike_count_n);

        // Test 3: Delta encoding - step changes > JUMP threshold
        $display("[%t] Test 3: Delta Encoding (with jumps > %0d)", $time, JUMP);
        encoding_select = 2'b10;
        spike_count_p = 0;
        spike_count_n = 0;
        run_delta_test();
        $display("[%t] Delta Encoding: Generated %0d spikeP, %0d spikeN", $time, spike_count_p, spike_count_n);

        // Test 4: Multispike encoding - ramp 0-15
        $display("[%t] Test 4: Multispike Encoding", $time);
        encoding_select = 2'b11;
        spike_count_p = 0;
        spike_count_n = 0;
        run_adc_ramp(0, 15, 1);
        $display("[%t] Multispike Encoding: Generated %0d spikeP, %0d spikeN", $time, spike_count_p, spike_count_n);

        repeat (100) @(posedge clk);
        $finish;
    end

    task automatic pulse_adc_valid;
        begin
            adc_valid = 1'b1;
            @(posedge clk);
            adc_valid = 1'b0;
        end
    endtask

    task automatic run_adc_ramp(int start_val, int end_val, int step);
        begin
            for (int value = start_val; value <= end_val; value = value + step) begin
                adc_data_in = value[3:0];

                // adc result becomes valid once per conversion frame
                repeat (499) @(posedge clk);
                pulse_adc_valid();
                
                // Wait for next sample period to start
                repeat (1) @(posedge clk);
            end
        end
    endtask

    task automatic run_delta_test;
        begin
            // Test sequence designed to trigger delta encoding
            // JUMP threshold = 5, so we need changes > 5
            
            // Start at 0
            adc_data_in = 4'd0;
            repeat (499) @(posedge clk);
            pulse_adc_valid();
            repeat (1) @(posedge clk);
            
            // Jump to 7 (change of +7 > JUMP)
            adc_data_in = 4'd7;
            repeat (499) @(posedge clk);
            pulse_adc_valid();
            repeat (1) @(posedge clk);
            
            // Jump to 1 (change of -6 > JUMP)
            adc_data_in = 4'd1;
            repeat (499) @(posedge clk);
            pulse_adc_valid();
            repeat (1) @(posedge clk);
            
            // Jump to 12 (change of +11 > JUMP)
            adc_data_in = 4'd12;
            repeat (499) @(posedge clk);
            pulse_adc_valid();
            repeat (1) @(posedge clk);
            
            // Jump to 4 (change of -8 > JUMP)
            adc_data_in = 4'd4;
            repeat (499) @(posedge clk);
            pulse_adc_valid();
            repeat (1) @(posedge clk);
            
            // Jump to 15 (change of +11 > JUMP)
            adc_data_in = 4'd15;
            repeat (499) @(posedge clk);
            pulse_adc_valid();
            repeat (1) @(posedge clk);
        end
    endtask

    // Monitor spikes
    always @(posedge clk) begin
        if (spikeP) spike_count_p = spike_count_p + 1;
        if (spikeN) spike_count_n = spike_count_n + 1;
    end

    initial begin
        $dumpfile("TOP_no_adc_tb.vcd");
        $dumpvars(0, TOP_no_adc_tb);
    end

endmodule

ASIC/sim/TOP_no_adc/TOP_no_adc_tb.vcd
$version Generated by VerilatedVcd $end
$timescale 1ps $end
 $scope module $rootio $end
 $upscope $end
 $scope module TOP_no_adc_tb $end
  $var wire 32 T WIDTH [31:0] $end
  $var wire 32 U LENGTH [31:0] $end
  $var wire 32 V MAX_SPIKES [31:0] $end
  $var wire 32 W JUMP [31:0] $end
  $var wire 32 X ADC_DIV [31:0] $end
  $var wire 32 Y ADC_COMP_DELAY [31:0] $end
  $var wire 1 M clk $end
  $var wire 1 N rst $end
  $var wire 1 O adc_valid $end
  $var wire 2 P encoding_select [1:0] $end
  $var wire 4 Q adc_data_in [3:0] $end
  $var wire 1 # spikeP [0:0] $end
  $var wire 1 $ spikeN [0:0] $end
  $var wire 32 R spike_count_p [31:0] $end
  $var wire 32 S spike_count_n [31:0] $end
  $scope module dut $end
   $var wire 32 T WIDTH [31:0] $end
   $var wire 32 U LENGTH [31:0] $end
   $var wire 32 V MAX_SPIKES [31:0] $end
   $var wire 32 W JUMP [31:0] $end
   $var wire 32 X ADC_DIV [31:0] $end
   $var wire 32 Y ADC_COMP_DELAY [31:0] $end
   $var wire 1 M clk $end
   $var wire 1 N rst $end
   $var wire 2 P encoding_select [1:0] $end
   $var wire 4 Q adc_data_in [3:0] $end
   $var wire 1 O adc_valid $end
   $var wire 1 # spikeP [0:0] $end
   $var wire 1 $ spikeN [0:0] $end
   $var wire 32 Z CNT_WIDTH [31:0] $end
   $var wire 1 * adc_clk $end
   $var wire 1 + adc_clk_comp $end
   $var wire 1 , sample_pulse $end
   $var wire 9 - adc_cnt [8:0] $end
   $var wire 1 . adc_valid_d $end
   $var wire 1 / adc_rst $end
   $var wire 4 0 adc_sample [3:0] $end
   $var wire 1 1 spikeP_rate [0:0] $end
   $var wire 1 [ spikeN_rate [0:0] $end
   $var wire 1 2 spikeP_temporal [0:0] $end
   $var wire 1 [ spikeN_temporal [0:0] $end
   $var wire 1 3 spikeP_delta [0:0] $end
   $var wire 1 4 spikeN_delta [0:0] $end
   $var wire 1 5 spikeP_multispike [0:0] $end
   $var wire 1 [ spikeN_multispike [0:0] $end
   $var wire 4 % clk_en [3:0] $end
   $scope module delta_encoder $end
    $var wire 32 T WIDTH [31:0] $end
    $var wire 32 U LENGTH [31:0] $end
    $var wire 32 W JUMP [31:0] $end
    $var wire 1 M clk $end
    $var wire 1 N rst $end
    $var wire 1 & clk_en $end
    $var wire 1 , sample_pulse $end
    $var wire 4 0 data_in [3:0] $end
    $var wire 16 \ divider [15:0] $end
    $var wire 1 3 spikeP [0:0] $end
    $var wire 1 4 spikeN [0:0] $end
    $var wire 4 6 data_in_array[0] [3:0] $end
    $var wire 4 7 previous[0] [3:0] $end
    $var wire 4 8 current[0] [3:0] $end
    $scope module unnamedblk1 $end
     $var wire 32 9 i [31:0] $end
    $upscope $end
    $scope module unnamedblk2 $end
     $var wire 32 : i [31:0] $end
    $upscope $end
   $upscope $end
   $scope module multispike_encoder $end
    $var wire 32 ] WIDTH [31:0] $end
    $var wire 32 ^ LENGTH [31:0] $end
    $var wire 32 _ MAX_SPIKES [31:0] $end
    $var wire 1 M clk $end
    $var wire 1 N rst $end
    $var wire 1 ' clk_en $end
    $var wire 1 , sample_pulse $end
    $var wire 4 0 data_in[0] [3:0] $end
    $var wire 16 \ divider [15:0] $end
    $var wire 1 5 spikeP [0:0] $end
    $var wire 1 [ spikeN [0:0] $end
    $var wire 32 ` SPIKE_BITS [31:0] $end
    $var wire 5 ; num_spikes[0] [4:0] $end
    $var wire 5 < spike_count[0] [4:0] $end
    $var wire 16 = spike_interval[0] [15:0] $end
    $var wire 16 > interval_counter[0] [15:0] $end
    $var wire 5 ? temp_spikes[0] [4:0] $end
    $scope module unnamedblk1 $end
     $var wire 32 @ i [31:0] $end
    $upscope $end
    $scope module unnamedblk2 $end
     $var wire 32 A i [31:0] $end
    $upscope $end
   $upscope $end
   $scope module rate_encoder $end
    $var wire 32 ] WIDTH [31:0] $end
    $var wire 32 ^ LENGTH [31:0] $end
    $var wire 1 M clk $end
    $var wire 1 N rst $end
    $var wire 1 ( clk_en $end
    $var wire 1 , sample_pulse $end
    $var wire 4 0 data_in [3:0] $end
    $var wire 16 \ divider [15:0] $end
    $var wire 1 1 spikeP [0:0] $end
    $var wire 1 [ spikeN [0:0] $end
    $var wire 4 B data_in_array[0] [3:0] $end
    $var wire 4 C rate_counter[0] [3:0] $end
    $var wire 4 D threshold[0] [3:0] $end
    $scope module unnamedblk1 $end
     $var wire 32 E i [31:0] $end
    $upscope $end
    $scope module unnamedblk2 $end
     $var wire 32 F i [31:0] $end
    $upscope $end
   $upscope $end
   $scope module temporal_encoder $end
    $var wire 32 ] WIDTH [31:0] $end
    $var wire 32 ^ LENGTH [31:0] $end
    $var wire 1 M clk $end
    $var wire 1 N rst $end
    $var wire 1 ) clk_en $end
    $var wire 1 , sample_pulse $end
    $var wire 4 0 data_in [3:0] $end
    $var wire 16 \ divider [15:0] $end
    $var wire 1 2 spikeP [0:0] $end
    $var wire 1 [ spikeN [0:0] $end
    $var wire 4 G data_in_array[0] [3:0] $end
    $var wire 16 H spike_location[0] [15:0] $end
    $var wire 16 I spike_counter[0] [15:0] $end
    $var wire 32 J location_calc[0] [31:0] $end
    $scope module unnamedblk1 $end
     $var wire 32 K i [31:0] $end
    $upscope $end
    $scope module unnamedblk2 $end
     $var wire 32 L i [31:0] $end
    $upscope $end
   $upscope $end
  $upscope $end
 $upscope $end
$enddefinitions $end


#0
0#
0$
b0001 %
0&
0'
1(
0)
0*
0+
0,
b000000000 -
0.
0/
b0000 0
01
02
03
04
05
b0000 6
b0000 7
b0000 8
b00000000000000000000000000000000 9
b00000000000000000000000000000000 :
b00000 ;
b00000 <
b0000000000000000 =
b0000000000000000 >
b00000 ?
b00000000000000000000000000000000 @
b00000000000000000000000000000000 A
b0000 B
b0000 C
b0000 D
b00000000000000000000000000000000 E
b00000000000000000000000000000000 F
b0000 G
b0000000000000000 H
b0000000000000000 I
b00000000000000000000000000000000 J
b00000000000000000000000000000000 K
b00000000000000000000000000000000 L
0M
1N
0O
b00 P
b0000 Q
b00000000000000000000000000000000 R
b00000000000000000000000000000000 S
b00000000000000000000000000000001 T
b00000000000000000000000000000100 U
b00000000000000000000000000010000 V
b00000000000000000000000000000101 W
b00000000000000000000000111110100 X
b00000000000000000000000000001000 Y
b00000000000000000000000000001001 Z
0[
b0000000111110100 \
b00000000000000000000000000000001 ]
b00000000000000000000000000000100 ^
b00000000000000000000000000010000 _
b00000000000000000000000000000101 `
#5000
b00000000000000000000000000000001 9
b1111111111111111 =
b00000000000000000000000000000001 @
b00000000000000000000000000000001 E
b00000000000000000000000000000001 K
1M
#10000
0M
#15000
1M
#20000
0M
#25000
1M
#30000
0M
#35000
1M
#40000
0M
#45000
1*
b000000001 -
b0001 C
b00000000000000000000000000000001 F
1M
0N
#50000
0M
#55000
b000000010 -
b0010 C
1M
#60000
0M
#65000
b000000011 -
b0011 C
1M
#70000
0M
#75000
b000000100 -
b0100 C
1M
#80000
0M
#85000
b000000101 -
b0101 C
1M
#90000
0M
#95000
b000000110 -
b0110 C
1M
#100000
0M
#105000
b000000111 -
b0111 C
1M
#110000
0M
#115000
b000001000 -
b1000 C
1M
#120000
0M
#125000
1+
b000001001 -
b1001 C
1M
#130000
0M
#135000
b000001010 -
b1010 C
1M
#140000
0M
#145000
b000001011 -
b1011 C
1M
#150000
0M
#155000
b000001100 -
b1100 C
1M
#160000
0M
#165000
b000001101 -
b1101 C
1M
#170000
0M
#175000
b000001110 -
b1110 C
1M
#180000
0M
#185000
b000001111 -
b1111 C
1M
#190000
0M
#195000
b000010000 -
b0000 C
1M
#200000
0M
#205000
b000010001 -
b0001 C
1M
#210000
0M
#215000
b000010010 -
b0010 C
1M
#220000
0M
#225000
b000010011 -
b0011 C
1M
#230000
0M
#235000
b000010100 -
b0100 C
1M
#240000
0M
#245000
b000010101 -
b0101 C
1M
#250000
0M
#255000
b000010110 -
b0110 C
1M
#260000
0M
#265000
b000010111 -
b0111 C
1M
#270000
0M
#275000
b000011000 -
b1000 C
1M
#280000
0M
#285000
b000011001 -
b1001 C
1M
#290000
0M
#295000
b000011010 -
b1010 C
1M
#300000
0M
#305000
b000011011 -
b1011 C
1M
#310000
0M
#315000
b000011100 -
b1100 C
1M
#320000
0M
#325000
b000011101 -
b1101 C
1M
#330000
0M
#335000
b000011110 -
b1110 C
1M
#340000
0M
#345000
b000011111 -
b1111 C
1M
#350000
0M
#355000
b000100000 -
b0000 C
1M
#360000
0M
#365000
b000100001 -
b0001 C
1M
#370000
0M
#375000
b000100010 -
b0010 C
1M
#380000
0M
#385000
b000100011 -
b0011 C
1M
#390000
0M
#395000
b000100100 -
b0100 C
1M
#400000
0M
#405000
b000100101 -
b0101 C
1M
#410000
0M
#415000
b000100110 -
b0110 C
1M
#420000
0M
#425000
b000100111 -
b0111 C
1M
#430000
0M
#435000
b000101000 -
b1000 C
1M
#440000
0M
#445000
b000101001 -
b1001 C
1M
#450000
0M
#455000
b000101010 -
b1010 C
1M
#460000
0M
#465000
b000101011 -
b1011 C
1M
#470000
0M
#475000
b000101100 -
b1100 C
1M
#480000
0M
#485000
b000101101 -
b1101 C
1M
#490000
0M
#495000
b000101110 -
b1110 C
1M
#500000
0M
#505000
b000101111 -
b1111 C
1M
#510000
0M
#515000
b000110000 -
b0000 C
1M
#520000
0M
#525000
b000110001 -
b0001 C
1M
#530000
0M
#535000
b000110010 -
b0010 C
1M
#540000
0M
#545000
b000110011 -
b0011 C
1M
#550000
0M
#555000
b000110100 -
b0100 C
1M
#560000
0M
#565000
b000110101 -
b0101 C
1M
#570000
0M
#575000
b000110110 -
b0110 C
1M
#580000
0M
#585000
b000110111 -
b0111 C
1M
#590000
0M
#595000
b000111000 -
b1000 C
1M
#600000
0M
#605000
b000111001 -
b1001 C
1M
#610000
0M
#615000
b000111010 -
b1010 C
1M
#620000
0M
#625000
b000111011 -
b1011 C
1M
#630000
0M
#635000
b000111100 -
b1100 C
1M
#640000
0M
#645000
b000111101 -
b1101 C
1M
#650000
0M
#655000
b000111110 -
b1110 C
1M
#660000
0M
#665000
b000111111 -
b1111 C
1M
#670000
0M
#675000
b001000000 -
b0000 C
1M
#680000
0M
#685000
b001000001 -
b0001 C
1M
#690000
0M
#695000
b001000010 -
b0010 C
1M
#700000
0M
#705000
b001000011 -
b0011 C
1M
#710000
0M
#715000
b001000100 -
b0100 C
1M
#720000
0M
#725000
b001000101 -
b0101 C
1M
#730000
0M
#735000
b001000110 -
b0110 C
1M
#740000
0M
#745000
b001000111 -
b0111 C
1M
#750000
0M
#755000
b001001000 -
b1000 C
1M
#760000
0M
#765000
b001001001 -
b1001 C
1M
#770000
0M
#775000
b001001010 -
b1010 C
1M
#780000
0M
#785000
b001001011 -
b1011 C
1M
#790000
0M
#795000
b001001100 -
b1100 C
1M
#800000
0M
#805000
b001001101 -
b1101 C
1M
#810000
0M
#815000
b001001110 -
b1110 C
1M
#820000
0M
#825000
b001001111 -
b1111 C
1M
#830000
0M
#835000
b001010000 -
b0000 C
1M
#840000
0M
#845000
b001010001 -
b0001 C
1M
#850000
0M
#855000
b001010010 -
b0010 C
1M
#860000
0M
#865000
b001010011 -
b0011 C
1M
#870000
0M
#875000
b001010100 -
b0100 C
1M
#880000
0M
#885000
b001010101 -
b0101 C
1M
#890000
0M
#895000
b001010110 -
b0110 C
1M
#900000
0M
#905000
b001010111 -
b0111 C
1M
#910000
0M
#915000
b001011000 -
b1000 C
1M
#920000
0M
#925000
b001011001 -
b1001 C
1M
#930000
0M
#935000
b001011010 -
b1010 C
1M
#940000
0M
#945000
b001011011 -
b1011 C
1M
#950000
0M
#955000
b001011100 -
b1100 C
1M
#960000
0M
#965000
b001011101 -
b1101 C
1M
#970000
0M
#975000
b001011110 -
b1110 C
1M
#980000
0M
#985000
b001011111 -
b1111 C
1M
#990000
0M
#995000
b001100000 -
b0000 C
1M
#1000000
0M
#1005000
b001100001 -
b0001 C
1M
#1010000
0M
#1015000
b001100010 -
b0010 C
1M
#1020000
0M
#1025000
b001100011 -
b0011 C
1M
#1030000
0M
#1035000
b001100100 -
b0100 C
1M
#1040000
0M
#1045000
b001100101 -
b0101 C
1M
#1050000
0M
#1055000
b001100110 -
b0110 C
1M
#1060000
0M
#1065000
b001100111 -
b0111 C
1M
#1070000
0M
#1075000
b001101000 -
b1000 C
1M
#1080000
0M
#1085000
b001101001 -
b1001 C
1M
#1090000
0M
#1095000
b001101010 -
b1010 C
1M
#1100000
0M
#1105000
b001101011 -
b1011 C
1M
#1110000
0M
#1115000
b001101100 -
b1100 C
1M
#1120000
0M
#1125000
b001101101 -
b1101 C
1M
#1130000
0M
#1135000
b001101110 -
b1110 C
1M
#1140000
0M
#1145000
b001101111 -
b1111 C
1M
#1150000
0M
#1155000
b001110000 -
b0000 C
1M
#1160000
0M
#1165000
b001110001 -
b0001 C
1M
#1170000
0M
#1175000
b001110010 -
b0010 C
1M
#1180000
0M
#1185000
b001110011 -
b0011 C
1M
#1190000
0M
#1195000
b001110100 -
b0100 C
1M
#1200000
0M
#1205000
b001110101 -
b0101 C
1M
#1210000
0M
#1215000
b001110110 -
b0110 C
1M
#1220000
0M
#1225000
b001110111 -
b0111 C
1M
#1230000
0M
#1235000
b001111000 -
b1000 C
1M
#1240000
0M
#1245000
b001111001 -
b1001 C
1M
#1250000
0M
#1255000
b001111010 -
b1010 C
1M
#1260000
0M
#1265000
b001111011 -
b1011 C
1M
#1270000
0M
#1275000
b001111100 -
b1100 C
1M
#1280000
0M
#1285000
b001111101 -
b1101 C
1M
#1290000
0M
#1295000
b001111110 -
b1110 C
1M
#1300000
0M
#1305000
b001111111 -
b1111 C
1M
#1310000
0M
#1315000
b010000000 -
b0000 C
1M
#1320000
0M
